semanticuiform/__init__.py
semanticuiform/config.py
semanticuiform/meta.py
semanticuiform/models.py
semanticuiform/tests.py
semanticuiform/templatetags/__init__.py
semanticuiform/templatetags/semanticui.py
semanticuiform/templates/semanticui/field.html
semanticuiform/templates/semanticui/form.html
semanticuiform/templates/semanticui/formset.html
django_semanticui_form-0.0.1.dist-info/top_level.txt
django_semanticui_form-0.0.1.dist-info/METADATA
django_semanticui_form-0.0.1.dist-info/DESCRIPTION.rst
django_semanticui_form-0.0.1.dist-info/metadata.json
django_semanticui_form-0.0.1.dist-info/WHEEL
django_semanticui_form-0.0.1.dist-info/RECORD
