Metadata-Version: 2.0
Name: django-semanticui-form
Version: 0.0.1
Summary: django-semanticui-form
Home-page: http://github.com/peterbe/django-semanticui-form
Author: Peter Bengtsson
Author-email: mail@peterbe.com
License: BSD
Keywords: SemanticUI,django
Platform: UNKNOWN
Classifier: Programming Language :: Python
Classifier: Topic :: Software Development :: Libraries :: Python Modules
Classifier: Framework :: Django
Classifier: Environment :: Web Environment
Classifier: Programming Language :: Python :: 2
Classifier: Programming Language :: Python :: 2.7
Classifier: Programming Language :: Python :: 3
Classifier: Programming Language :: Python :: 3.3
Classifier: Programming Language :: Python :: 3.4
Requires-Dist: django (>=1.3)
